MANIFEST.in
README.rst
setup.py
hearthstonearenalogwatcher/__init__.py
hearthstonearenalogwatcher.egg-info/PKG-INFO
hearthstonearenalogwatcher.egg-info/SOURCES.txt
hearthstonearenalogwatcher.egg-info/dependency_links.txt
hearthstonearenalogwatcher.egg-info/not-zip-safe
hearthstonearenalogwatcher.egg-info/top_level.txt