Metadata-Version: 1.0
Name: hearthstonearenalogwatcher
Version: 0.1.1
Summary: provide an interface for getting hearthstone arena events: entering, exiting, hero selected, card drafted
Home-page: https://www.github.com/russon77/hearthstonearenalogwatcher
Author: Tristan Kernan
Author-email: russon77@gmail.com
License: MIT
Keywords: hearthstone
Platform: UNKNOWN
